somvec/SomWeightInit.py
somvec/__init__.py
somvec-0.1.2.dist-info/METADATA
somvec-0.1.2.dist-info/WHEEL
somvec-0.1.2.dist-info/top_level.txt
somvec-0.1.2.dist-info/RECORD
