Metadata-Version: 2.1
Name: somvec
Version: 0.1.2
Summary: A vectorised implementation of the Self-Organising Map (SOM) algorithm
Home-page: https://bitbucket.org/GeoffreyClark/somvec
Author: Geoffrey Clark
Author-email: geoffreyrussellclark@gmail.com
License: MIT
Platform: UNKNOWN
Classifier: Programming Language :: Python :: 3
Classifier: License :: OSI Approved :: MIT License
Classifier: Operating System :: OS Independent
